tasket/__init__.py
tasket/constants.py
tasket/database.py
tasket/tasket.py
tasket/ttasket.py
tasket/typer-tasket.py
tasket-0.0.4.dist-info/entry_points.txt
tasket-0.0.4.dist-info/LICENSE
tasket-0.0.4.dist-info/WHEEL
tasket-0.0.4.dist-info/METADATA
tasket-0.0.4.dist-info/RECORD
